vrp_multi_exec/entry_points/multi_exec.py
vrp_multi_exec/lib/__init__.py
vrp_multi_exec/lib/handlers/__init__.py
vrp_multi_exec/lib/handlers/device_config_handler.py
vrp_multi_exec/lib/logging/__init__.py
vrp_multi_exec/lib/parsers/__init__.py
vrp_multi_exec/lib/parsers/base.py
vrp_multi_exec/lib/parsers/config.py
vrp_multi_exec/lib/parsers/targets.py
vrp_multi_exec/lib/parsers/vars.py
vrp_multi_exec/lib/ssh_tools.py
vrp_multi_exec-0.1.1.dist-info/entry_points.txt
vrp_multi_exec-0.1.1.dist-info/LICENSE
vrp_multi_exec-0.1.1.dist-info/WHEEL
vrp_multi_exec-0.1.1.dist-info/METADATA
vrp_multi_exec-0.1.1.dist-info/RECORD
