Metadata-Version: 2.1
Name: vrp-multi-exec
Version: 0.1.1
Summary: 
License: GPL-3.0
Author: Maged Motawea
Author-email: magedmotawea@gmail.com
Requires-Python: >=3.6,<4.0
Classifier: License :: OSI Approved :: GNU General Public License v3 (GPLv3)
Classifier: Programming Language :: Python :: 3
Classifier: Programming Language :: Python :: 3.6
Classifier: Programming Language :: Python :: 3.7
Classifier: Programming Language :: Python :: 3.8
Classifier: Programming Language :: Python :: 3.9
Requires-Dist: Jinja2 (>=2.11.3,<3.0.0)
Requires-Dist: PyYAML (>=5.4.1,<6.0.0)
Requires-Dist: click (>=7.1.2,<8.0.0)
Requires-Dist: gevent (>=21.1.2,<22.0.0)
Requires-Dist: loguru (>=0.5.3,<0.6.0)
Requires-Dist: paramiko (>=2.7.2,<3.0.0)
